msctl/__init__.py
msctl/cli.py
msctl/commands/__init__.py
msctl/commands/manager_cmd.py
msctl-0.1.0.dist-info/METADATA
msctl-0.1.0.dist-info/WHEEL
msctl-0.1.0.dist-info/entry_points.txt
msctl-0.1.0.dist-info/licenses/LICENSE
msctl-0.1.0.dist-info/RECORD
