Metadata-Version: 2.4
Name: msctl
Version: 0.1.0
Summary: Microservices Manager CLI
Author-email: Alok <your.email@example.com>
License: MIT License
License-File: LICENSE
Classifier: License :: OSI Approved :: MIT License
Classifier: Operating System :: OS Independent
Classifier: Programming Language :: Python :: 3
Requires-Python: >=3.7
Requires-Dist: click>=8.0.0
